MANIFEST.in
README.md
setup.py
.piptui/config.ini
.piptui/themes/black_on_white.json
.piptui/themes/colorful.json
.piptui/themes/elegant.json
.piptui/themes/transparent.json
PipTUI.egg-info/PKG-INFO
PipTUI.egg-info/SOURCES.txt
PipTUI.egg-info/dependency_links.txt
PipTUI.egg-info/entry_points.txt
PipTUI.egg-info/requires.txt
PipTUI.egg-info/top_level.txt
piptui/__init__.py
piptui/__main__.py
piptui/__version__.py
piptui/actionForms.py
piptui/app.py
piptui/infoBox.py
piptui/logBox.py
piptui/mainForm.py
piptui/pkgBox.py
piptui/pkgInfoForm.py
piptui/run_threaded.py
piptui/searchBox.py
piptui/settings.py
piptui/settingsForm.py
piptui/custom/__init__.py
piptui/custom/apNPSApplicationEvents.py
piptui/custom/customForm.py
piptui/custom/customTheme.py