Metadata-Version: 1.1
Name: PipTUI
Version: 0.3.8
Summary: A console PIP GUI!
Home-page: UNKNOWN
Author: Nitan Alexandru Marcel
Author-email: nitan.marcel@gmail.com
License: MIT
Keywords: pip,npyscreen,pip-gui
Platform: UNKNOWN
Classifier: Environment :: Console
Classifier: Development Status :: 4 - Beta
Classifier: License :: OSI Approved :: MIT License
Classifier: Operating System :: OS Independent
Classifier: Programming Language :: Python
Classifier: Programming Language :: Python :: 3.6
Classifier: Programming Language :: Python :: 3.7
